viral/__init__.py
viral/base.py
viral/get_viral_data.py
viral-0.0.3.dist-info/LICENSE
viral-0.0.3.dist-info/METADATA
viral-0.0.3.dist-info/WHEEL
viral-0.0.3.dist-info/top_level.txt
viral-0.0.3.dist-info/RECORD
