Metadata-Version: 2.1
Name: viral
Version: 0.0.3
Summary: Acquiring and analyzing covid-19 (coronavirus) statistics data
Home-page: https://github.com/thorwhalen/viral
Author: Thor Whalen
License: apache-2.0
Platform: any
Requires-Dist: py2store
Requires-Dist: pandas
Requires-Dist: kaggle
